devtools_hash/__init__.py
devtools_hash-1.0.1.dist-info/METADATA
devtools_hash-1.0.1.dist-info/WHEEL
devtools_hash-1.0.1.dist-info/top_level.txt
devtools_hash-1.0.1.dist-info/RECORD
