Metadata-Version: 2.1
Name: devtools-hash
Version: 1.0.1
Summary: Hash generator (MD5, SHA)
Home-page: https://devtools.at/tools/hash-generator
Author: DevTools.at
Author-email: hello@devtools.at
Project-URL: Homepage, https://devtools.at/tools/hash-generator
Project-URL: Repository, https://github.com/devtools-at/hash-generator
Classifier: Development Status :: 4 - Beta
Classifier: Intended Audience :: Developers
Classifier: License :: OSI Approved :: MIT License
Classifier: Programming Language :: Python :: 3
Requires-Python: >=3.8
